cacheops/__init__.py
cacheops/apps.py
cacheops/conf.py
cacheops/cross.py
cacheops/getset.py
cacheops/invalidation.py
cacheops/jinja2.py
cacheops/query.py
cacheops/reaper.py
cacheops/redis.py
cacheops/serializers.py
cacheops/sharding.py
cacheops/signals.py
cacheops/simple.py
cacheops/transaction.py
cacheops/tree.py
cacheops/utils.py
cacheops/lua/cache_thing.lua
cacheops/lua/cache_thing_insideout.lua
cacheops/lua/invalidate.lua
cacheops/lua/invalidate_insideout.lua
cacheops/management/__init__.py
cacheops/management/commands/__init__.py
cacheops/management/commands/cleanfilecache.py
cacheops/management/commands/invalidate.py
cacheops/management/commands/reapconjs.py
cacheops/templatetags/__init__.py
cacheops/templatetags/cacheops.py
django_cacheops-7.1.dist-info/LICENSE
django_cacheops-7.1.dist-info/METADATA
django_cacheops-7.1.dist-info/WHEEL
django_cacheops-7.1.dist-info/pbr.json
django_cacheops-7.1.dist-info/top_level.txt
django_cacheops-7.1.dist-info/RECORD
